<?xml version="1.0" encoding="utf-8"?>
<PlayerData xmlns:xsi="http://www.w3.org/2001/XMLSchema-instance" xmlns:xsd="http://www.w3.org/2001/XMLSchema">
  <charName>Blue</charName>
  <level>1</level>
  <def>1</def>
  <hp>2</hp>
  <mp>1.5</mp>
  <modelAdress>Prefabs/PlayerChar/Warrior_0</modelAdress>
  <d_TCList>
    <string>Move2</string>
    <string>Forest</string>
    <string>Cave</string>
    <string>Dungeon</string>
  </d_TCList>
  <d_TCDeck>
    <string>Move2</string>
    <string>Forest</string>
    <string>Cave</string>
    <string>Dungeon</string>
    <string>Move2</string>
    <string>Forest</string>
    <string>Cave</string>
    <string>Dungeon</string>
  </d_TCDeck>
  <d_BCList>
    <string>Punch</string>
    <string>Slash_1</string>
    <string>Guard</string>
    <string>X</string>
  </d_BCList>
  <d_BCDeck>
    <string>Punch</string>
    <string>Slash_1</string>
    <string>Guard</string>
    <string>X</string>
  </d_BCDeck>
</PlayerData>